archette/__init__.py
archette/garch.py
archette-0.1.1.dist-info/LICENSE
archette-0.1.1.dist-info/METADATA
archette-0.1.1.dist-info/WHEEL
archette-0.1.1.dist-info/top_level.txt
archette-0.1.1.dist-info/RECORD
