Metadata-Version: 2.1
Name: archette
Version: 0.1.1
Summary: tiny arch
Requires-Python: >=3.9
License-File: LICENSE
Requires-Dist: numba>=0.53.1
Requires-Dist: numpy>=2.0.2
Requires-Dist: scipy>=1.13.1
